{
	"name": "crypto_secretbox_easy",
	"dependencies": ["_crypto_secretbox_keybytes", "_crypto_secretbox_macbytes", "_crypto_secretbox_noncebytes"],
	"type": "function",
	"inputs": [
		{
			"name": "message",
			"type": "unsized_buffer"
		},
		{
			"name": "nonce",
			"type": "buffer",
			"size": "libsodium_raw._crypto_secretbox_noncebytes()"
		},
		{
			"name": "key",
			"type": "buffer",
			"size": "libsodium_raw._crypto_secretbox_keybytes()"
		}
	],
	"outputs": [
		{
			"name": "cipher",
			"type": "buffer",
			"size": "message_size + libsodium_raw._crypto_secretbox_macbytes()"
		}
	],
	"target": "libsodium_raw._crypto_secretbox_easy(cipher_byte, message_byte, message_size, 0, nonce_byte, key_byte);",
	"return": "return encodeResult(cipher, resultEncoding)"
}
